Workbook

Sheet Summary
A1: Modern SIT Test Case Workbook
A2: Source Context | B2: Retail POS Platform Migration System Integration Test Plan (sanitized source basis)
A3: Workbook Purpose | B3: Portfolio-ready test cases covering POS, EFT, gift cards, returns/customer ID, and regression traceability.
A5: Execution Dashboard
A6: Sheet | B6: Total Cases | C6: Pass | D6: Fail | E6: Blocked | F6: Not Run | G6: Pass Rate
A7: POS_Transactions | B7: =COUNTA('POS_Transactions'!A:A)-1 | C7: =COUNTIF('POS_Transactions'!N:N,"Pass") | D7: =COUNTIF('POS_Transactions'!N:N,"Fail") | E7: =COUNTIF('POS_Transactions'!N:N,"Blocked") | F7: =COUNTIF('POS_Transactions'!N:N,"Not Run") | G7: =IF(B7=0,0,C7/B7)
A8: Payment_Flows | B8: =COUNTA('Payment_Flows'!A:A)-1 | C8: =COUNTIF('Payment_Flows'!N:N,"Pass") | D8: =COUNTIF('Payment_Flows'!N:N,"Fail") | E8: =COUNTIF('Payment_Flows'!N:N,"Blocked") | F8: =COUNTIF('Payment_Flows'!N:N,"Not Run") | G8: =IF(B8=0,0,C8/B8)
A9: GiftCard_Flows | B9: =COUNTA('GiftCard_Flows'!A:A)-1 | C9: =COUNTIF('GiftCard_Flows'!N:N,"Pass") | D9: =COUNTIF('GiftCard_Flows'!N:N,"Fail") | E9: =COUNTIF('GiftCard_Flows'!N:N,"Blocked") | F9: =COUNTIF('GiftCard_Flows'!N:N,"Not Run") | G9: =IF(B9=0,0,C9/B9)
A10: Returns_ID | B10: =COUNTA('Returns_ID'!A:A)-1 | C10: =COUNTIF('Returns_ID'!N:N,"Pass") | D10: =COUNTIF('Returns_ID'!N:N,"Fail") | E10: =COUNTIF('Returns_ID'!N:N,"Blocked") | F10: =COUNTIF('Returns_ID'!N:N,"Not Run") | G10: =IF(B10=0,0,C10/B10)
A12: Overall | B12: =SUM(B7:B10) | C12: =SUM(C7:C10) | D12: =SUM(D7:D10) | E12: =SUM(E7:E10) | F12: =SUM(F7:F10) | G12: =IF(B12=0,0,C12/B12)
A15: Release-readiness checks
A16: P1/P2 open defects | B16: 0 before release sign-off
A17: Critical business flows | B17: Sale, EFT, Gift Card, Return + DL all passed
A18: Audit Log validation | B18: Verified for critical scenarios
A19: Offline / degraded mode | B19: Executed at least one happy path + one recovery path

Sheet POS_Transactions
A1: TC_ID | B1: Requirement_ID | C1: Release | D1: Module | E1: Scenario | F1: Preconditions | G1: Steps | H1: Expected_Result | I1: Priority | J1: Type | K1: Automation_Candidate | L1: Layer | M1: Test_Data | N1: Status | O1: Defect_ID | P1: Notes
A2: POS-001 | B2: REQ-POS-001 | C2: Phase 1 | D2: POS | E2: Change quantity on standard item from any DynaFrame | F2: Cashier logged in; sale started | G2: 1. Scan standard item 2. Open alternate DynaFrame 3. Tap Super Change Quantity 4. Update qty to 3 | H2: Quantity changes to 3; line total updates; Audit Log records soft key usage | I2: High | J2: Functional | K2: Yes | L2: UI + Audit Log | M2: Standard grocery SKU | N2: Not Run | P2: Validate Audit Log event code
A3: POS-002 | B3: REQ-POS-001 | C3: Phase 1 | D3: POS | E3: Attempt quantity change on restricted item | F3: Gift card item available in sale | G3: 1. Scan gift card 2. Tap Super Change Quantity | H3: System blocks quantity change for restricted item and shows correct message | I3: High | J3: Negative | K3: Yes | L3: UI | M3: Gift card SKU | N3: Not Run | P3: Ensure same rules as legacy quantity control
A4: POS-003 | B4: REQ-RCT-001 | C4: Phase 1 | D4: Receipts | E4: Combined customer/EFT receipt enabled | F4: Combined EFT receipt config ON | G4: 1. Complete EFT purchase 2. Capture receipt output | H4: Itemized receipt and customer EFT receipt print contiguously with no knife cut; store copy separated | I4: Critical | J4: Functional | K4: Partial | L4: UI + Printer | M4: Debit card test account | N4: Not Run | P4: Verify masked PAN last 4 only
A5: POS-004 | B5: REQ-RCT-001 | C5: Phase 1 | D5: Receipts | E5: Multiple EFT tenders print contiguously | F5: Combined EFT receipt config ON; split tender allowed | G5: 1. Start sale 2. Tender with two EFT methods 3. Print receipts | H5: Customer EFT receipts are contiguous; store EFT receipts are contiguous; masking preserved | I5: Critical | J5: Functional | K5: Partial | L5: UI + Printer | M5: Two test cards | N5: Not Run | P5: Check no trailer after itemized receipt
A6: POS-005 | B6: N/A | C6: Regression | D6: POS | E6: Healthy mode sale transaction | F6: Lane online and synced | G6: 1. Scan 3 items 2. Tender cash 3. Finalize sale | H6: Sale completes, receipt prints, totals match Audit Log | I6: Critical | J6: Regression | K6: Yes | L6: E2E | M6: Cash sale basket | N6: Not Run | P6: Baseline store transaction
A7: POS-006 | B7: N/A | C7: Regression | D7: POS | E7: Degraded/offline sale transaction | F7: Disconnect upstream network; lane in degraded mode | G7: 1. Scan 2 items 2. Tender allowed offline type 3. Reconnect network | H7: Sale completes per degraded rules; reconciliation occurs after reconnect | I7: Critical | J7: E2E | K7: Partial | L7: UI + Store Server | M7: Offline allowed tender | N7: Not Run | P7: Capture reconciliation evidence
A8: POS-007 | B8: REQ-PRM-001 | C8: Phase 2 | D8: Promotions | E8: Virtual amount-off promotion triggers above threshold | F8: Promo configured in WebOffice | G8: 1. Scan threshold quantity + 1 2. Review discounts | H8: Promotion triggers only when reward trigger threshold exceeded | I8: High | J8: Functional | K8: Yes | L8: UI + Config | M8: Simple promo item set | N8: Not Run | P8: Validate sales quantity trigger count
A9: POS-008 | B9: REQ-PRM-001 | C9: Phase 2 | D9: Promotions | E9: Virtual percent-off promotion limits trigger count | F9: Promo configured with sales quantity limit | G9: 1. Ring qualifying item repeatedly 2. Review discounts | H9: Promotion does not exceed allowed trigger count in one transaction | I9: High | J9: Boundary | K9: Yes | L9: UI + Config | M9: Percent promo item set | N9: Not Run | P9: Boundary test

Sheet Payment_Flows
A1: TC_ID | B1: Requirement_ID | C1: Release | D1: Module | E1: Scenario | F1: Preconditions | G1: Steps | H1: Expected_Result | I1: Priority | J1: Type | K1: Automation_Candidate | L1: Layer | M1: Test_Data | N1: Status | O1: Defect_ID | P1: Notes
A2: PAY-001 | B2: REQ-INT-001 | C2: Phase 1 | D2: EFT/External Host Service | E2: Approved EFT authorization | F2: Lane online; gateway reachable | G2: 1. Build sale 2. Tender EFT 3. Approve on PIN pad | H2: Authorization approved; approval code stored; receipt and Audit Log consistent | I2: Critical | J2: E2E | K2: Yes | L2: UI + API + Audit Log | M2: Approved EFT card | N2: Not Run | P2: Check External Host Service response mapping
A3: PAY-002 | B3: REQ-INT-001 | C3: Phase 1 | D3: EFT/External Host Service | E3: Declined EFT authorization with velocity message | F3: Gateway returns decline with <=5 lines velocity info | G3: 1. Build sale 2. Tender EFT using decline card | H3: Decline shown with velocity message; no duplicate charge; decline receipt behavior follows config | I3: Critical | J3: Negative | K3: Yes | L3: UI + API | M3: Decline card | N3: Not Run | P3: Validate cashier override rules
A4: PAY-003 | B4: REQ-INT-001 | C4: Phase 1 | D4: EFT/External Host Service | E4: Gateway timeout + retry protection | F4: Simulated gateway timeout | G4: 1. Tender EFT 2. Wait for timeout 3. Retry same tender | H4: System handles timeout gracefully; idempotency prevents duplicate authorization | I4: Critical | J4: Recovery | K4: Yes | L4: API + Backend | M4: Timeout scenario card | N4: Not Run | P4: Use Postman idempotency key
A5: PAY-004 | B5: REQ-RCT-001 | C5: Phase 1 | D5: Receipts | E5: Masked account number on EFT receipt | F5: Any EFT card accepted | G5: 1. Complete EFT sale 2. Inspect receipt and journal | H5: Only last four digits printed; all other digits masked | I5: High | J5: Security | K5: Partial | L5: Printer + Audit Log | M5: Approved EFT card | N5: Not Run | P5: PCI-style masking check
A6: PAY-005 | B6: N/A | C6: Regression | D6: Payments | E6: Offline EFT not permitted path | F6: Lane in degraded mode; EFT disabled offline | G6: 1. Attempt EFT while offline | H6: System blocks unsupported offline EFT and displays correct fallback guidance | I6: High | J6: Negative | K6: Yes | L6: UI | M6: Offline lane state | N6: Not Run
A7: PAY-006 | B7: REQ-INT-001 | C7: Phase 1 | D7: External Host Service | E7: Display signature on DynaKey for cashier verification | F7: Signature-capable card and DynaKey available | G7: 1. Complete signature-required EFT 2. Observe DynaKey screen | H7: Customer signature displays on DynaKey and cashier can verify before completion | I7: High | J7: Functional | K7: No | L7: Hardware + UI | M7: Signature card | N7: Not Run | P7: Hardware dependent
A8: PAY-007 | B8: REQ-INT-001 | C8: Phase 1 | D8: External Host Service | E8: Upromise cards bypass host activation | F8: Upromise test card configured | G8: 1. Scan Upromise card 2. Finalize transaction | H8: Card not sent to External Host Service host for activation | I8: Medium | J8: Functional | K8: Yes | L8: API | M8: Upromise test card | N8: Not Run | P8: API log validation

Sheet GiftCard_Flows
A1: TC_ID | B1: Requirement_ID | C1: Release | D1: Module | E1: Scenario | F1: Preconditions | G1: Steps | H1: Expected_Result | I1: Priority | J1: Type | K1: Automation_Candidate | L1: Layer | M1: Test_Data | N1: Status | O1: Defect_ID | P1: Notes
A2: GC-001 | B2: REQ-GC-001 | C2: Phase 1 | D2: Gift Card | E2: Prompt mini shown when gift card scanned | F2: Gift card prompt feature enabled | G2: 1. Scan gift card during sale | H2: New prompt displays with OK and Cancel options | I2: High | J2: Functional | K2: Yes | L2: UI | M2: Gift card barcode | N2: Not Run
A3: GC-002 | B3: REQ-GC-001 | C3: Phase 1 | D3: Gift Card | E3: Cancel bypasses activation | F3: Prompt displayed | G3: 1. Scan gift card 2. Select Cancel | H3: Activation bypassed and transaction continues | I3: High | J3: Negative | K3: Yes | L3: UI + API | M3: Gift card barcode | N3: Not Run | P3: Ensure no host call generated
A4: GC-003 | B4: REQ-GC-001 | C4: Phase 1 | D4: Gift Card | E4: OK triggers activation and continues | F4: Prompt displayed | G4: 1. Scan gift card 2. Select OK 3. Tender sale | H4: Activation attempted and sale continues to completion | I4: Critical | J4: E2E | K4: Yes | L4: UI + API | M4: Gift card barcode | N4: Not Run | P4: Capture activation response
A5: GC-004 | B5: REQ-GC-002 | C5: Phase 1 | D5: Gift Card Provider | E5: Gift Card Provider UPC128 fixed denomination activation | F5: Gift Card Provider SKU configured | G5: 1. Scan Gift Card Provider card 2. Finalize transaction | H5: Activation succeeds after final tender; receipt includes activation section | I5: Critical | J5: E2E | K5: Yes | L5: UI + API + Printer | M5: Gift Card Provider fixed denom card | N5: Not Run
A6: GC-005 | B6: REQ-GC-002 | C6: Phase 1 | D6: Gift Card Provider | E6: Variable denomination activation + optional fee | F6: Fee-enabled configuration active | G6: 1. Scan variable card 2. Enter amount 3. Finalize transaction | H6: Card activates for entered amount; optional fee applied correctly | I6: Critical | J6: Boundary | K6: Yes | L6: UI + API | M6: Variable denomination card | N6: Not Run | P6: Check fee line item
A7: GC-006 | B7: REQ-GC-002 | C7: Phase 1 | D7: Gift Card Provider | E7: Duplicate sale prevention in same transaction | F7: Single Gift Card Provider card available | G7: 1. Scan same card twice in one transaction | H7: System prevents second sale of same card in same transaction | I7: Critical | J7: Negative | K7: Yes | L7: UI + API | M7: Duplicate card scan | N7: Not Run | P7: Idempotency / duplicate control
A8: GC-007 | B8: REQ-GC-002 | C8: Phase 1 | D8: Gift Card Provider | E8: Voided card is not activated | F8: Card scanned but voided before tender | G8: 1. Scan Gift Card Provider card 2. Void item 3. Finalize transaction | H8: Voided card is not activated | I8: Critical | J8: Negative | K8: Yes | L8: UI + API | M8: Void before tender | N8: Not Run
A9: GC-008 | B9: REQ-GC-002 | C9: Phase 1 | D9: Gift Card Provider | E9: Suspend blocked when Gift Card Provider card present | F9: Suspend allowed generally | G9: 1. Scan Gift Card Provider card 2. Attempt suspend | H9: Suspend disallowed until card item is voided | I9: High | J9: Negative | K9: Yes | L9: UI | M9: Gift Card Provider card | N9: Not Run
A10: GC-009 | B10: REQ-GC-002 | C10: Phase 1 | D10: Gift Card Provider | E10: Non-UPC128 Gift Card Provider activation blocked | F10: UPC-A/non-supported card available | G10: 1. Scan non-UPC128 card | H10: System disallows activation of unsupported format | I10: High | J10: Negative | K10: Yes | L10: UI | M10: Unsupported card | N10: Not Run

Sheet Returns_DL
A1: TC_ID | B1: Requirement_ID | C1: Release | D1: Module | E1: Scenario | F1: Preconditions | G1: Steps | H1: Expected_Result | I1: Priority | J1: Type | K1: Automation_Candidate | L1: Layer | M1: Test_Data | N1: Status | O1: Defect_ID | P1: Notes
A2: RET-001 | B2: REQ-RET-001 | C2: Phase 1 | D2: Returns | E2: DL scan prompt displayed when return mode initiated | F2: WebOffice option enabled | G2: 1. Initiate return 2. Observe prompt | H2: Return flow prompts for DL scan/swipe/key entry | I2: Critical | J2: Functional | K2: Yes | L2: UI + Config | M2: Returnable item | N2: Not Run
A3: RET-002 | B3: REQ-RET-001 | C3: Phase 1 | D3: Returns | E3: DL prompt suppressed when configuration disabled | F3: WebOffice option disabled | G3: 1. Initiate return | H3: DL prompt not shown; return follows disabled behavior | I3: High | J3: Configuration | K3: Yes | L3: UI + Config | M3: Returnable item | N3: Not Run
A4: RET-003 | B4: REQ-RET-001 | C4: Phase 1 | D4: Returns | E4: Barcode scan captures DL state and number | F4: 2D scanner connected | G4: 1. Start return 2. Scan DL barcode | H4: DL number and state parsed correctly and written to Audit Log | I4: Critical | J4: E2E | K4: Yes | L4: Hardware + Audit Log | M4: Driver license barcode | N4: Not Run | P4: Capture Audit Log source=barcode
A5: RET-004 | B5: REQ-RET-001 | C5: Phase 1 | D5: Returns | E5: MSR swipe captures DL data | F5: PIN/DynaKey MSR available | G5: 1. Start return 2. Swipe DL via MSR | H5: DL state and number captured and written to Audit Log with source=swipe | I5: Critical | J5: E2E | K5: Yes | L5: Hardware + Audit Log | M5: Driver license magnetic stripe | N5: Not Run
A6: RET-005 | B6: REQ-RET-001 | C6: Phase 1 | D6: Returns | E6: Manual key entry fallback | F6: Scanner unavailable | G6: 1. Start return 2. Key DL number and state manually | H6: Manual entry accepted when enabled and Audit Log source=manual | I6: High | J6: Recovery | K6: Yes | L6: UI + Audit Log | M6: Manual DL value | N6: Not Run
A7: RET-006 | B7: N/A | C7: Regression | D7: Returns | E7: Refund amount matches original tender | F7: Original sale exists | G7: 1. Retrieve original sale 2. Process return | H7: Refund amount and tender mapping match original sale; audit trail preserved | I7: Critical | J7: Regression | K7: Partial | L7: UI + Backend | M7: Original receipt | N7: Not Run

Sheet Regression_Traceability
A1: Requirement_ID | B1: Feature | C1: Mapped_Test_Cases | D1: Business_Flow | E1: Validation_Layers | F1: Risk | G1: Release
A2: REQ-GC-001 | B2: Gift Card Prompt Mini | C2: GC-001, GC-002, GC-003 | D2: Gift card activation decisioning | E2: UI, API | F2: High | G2: Phase 1
A3: REQ-POS-001 | B3: Super Change Quantity Key | C3: POS-001, POS-002 | D3: Cashier item quantity control | E3: UI, Audit Log | F3: High | G3: Phase 1
A4: REQ-RCT-001 | B4: Combined customer/EFT receipt | C4: POS-003, POS-004, PAY-004 | D4: Receipt printing and masking | E4: Printer, UI, Audit Log | F4: Critical | G4: Phase 1
A5: REQ-INT-001 | B5: External Host Service Integration Plus | C5: PAY-001, PAY-002, PAY-003, PAY-006, PAY-007 | D5: Payment authorization and host integration | E5: UI, API, Hardware | F5: Critical | G5: Phase 1
A6: REQ-RET-001 | B6: Swiped DL Data to Audit Log During Return | C6: RET-001, RET-002, RET-003, RET-004, RET-005 | D6: Return with ID capture | E6: UI, Hardware, Audit Log | F6: Critical | G6: Phase 1
A7: REQ-GC-002 | B7: Gift Card Provider Gift Card | C7: GC-004, GC-005, GC-006, GC-007, GC-008, GC-009 | D7: Gift card activation / reload / controls | E7: UI, API, Printer | F7: Critical | G7: Phase 1
A8: REQ-PRM-001 | B8: CM Virtual Support | C8: POS-007, POS-008 | D8: Promotion triggering logic | E8: UI, Config | F8: High | G8: Phase 2
